MANIFEST.in
README.md
setup.py
django_redis_status.egg-info/PKG-INFO
django_redis_status.egg-info/SOURCES.txt
django_redis_status.egg-info/dependency_links.txt
django_redis_status.egg-info/not-zip-safe
django_redis_status.egg-info/top_level.txt
redis_status/__init__.py
redis_status/admin.py
redis_status/templates/redis_status/index.html
redis_status/templatetags/.DS_Store
redis_status/templatetags/__init__.py
redis_status/templatetags/redis_status_tags.py