Metadata-Version: 1.0
Name: django-redis-status
Version: 1.0.0
Summary: A django application that displays some statistics about your redis instance in the admin.
Home-page: https://github.com/nicholasserra/django-redis-status
Author: Nicholas Serra
Author-email: nick@528hazelwood.com
License: UNKNOWN
Platform: UNKNOWN
Classifier: Development Status :: 4 - Beta
Classifier: Environment :: Web Environment
Classifier: Intended Audience :: Developers
Classifier: License :: OSI Approved :: BSD License
Classifier: Operating System :: OS Independent
Classifier: Programming Language :: Python
Classifier: Framework :: Django
